WindowsAppYingyongKaifaJiaocheng/README.md
WindowsAppYingyongKaifaJiaocheng/__init__.py
WindowsAppYingyongKaifaJiaocheng/__main__.py
WindowsAppYingyongKaifaJiaocheng/file.epub
WindowsAppYingyongKaifaJiaocheng/index.html
WindowsAppYingyongKaifaJiaocheng/css/__init__.py
WindowsAppYingyongKaifaJiaocheng/css/annotations.css
WindowsAppYingyongKaifaJiaocheng/css/main.css
WindowsAppYingyongKaifaJiaocheng/css/normalize.css
WindowsAppYingyongKaifaJiaocheng/css/popup.css
WindowsAppYingyongKaifaJiaocheng/font/__init__.py
WindowsAppYingyongKaifaJiaocheng/font/fontello.eot
WindowsAppYingyongKaifaJiaocheng/font/fontello.svg
WindowsAppYingyongKaifaJiaocheng/font/fontello.ttf
WindowsAppYingyongKaifaJiaocheng/font/fontello.woff
WindowsAppYingyongKaifaJiaocheng/img/__init__.py
WindowsAppYingyongKaifaJiaocheng/img/annotator-glyph-sprite.png
WindowsAppYingyongKaifaJiaocheng/img/annotator-icon-sprite.png
WindowsAppYingyongKaifaJiaocheng/img/apple-touch-icon.png
WindowsAppYingyongKaifaJiaocheng/img/cancelfullscreen.png
WindowsAppYingyongKaifaJiaocheng/img/close.png
WindowsAppYingyongKaifaJiaocheng/img/fullscreen.png
WindowsAppYingyongKaifaJiaocheng/img/loader.gif
WindowsAppYingyongKaifaJiaocheng/img/menu-icon.png
WindowsAppYingyongKaifaJiaocheng/img/save.png
WindowsAppYingyongKaifaJiaocheng/img/saved.png
WindowsAppYingyongKaifaJiaocheng/img/settings-s.png
WindowsAppYingyongKaifaJiaocheng/img/settings.png
WindowsAppYingyongKaifaJiaocheng/img/star.png
WindowsAppYingyongKaifaJiaocheng/js/__init__.py
WindowsAppYingyongKaifaJiaocheng/js/epub.js
WindowsAppYingyongKaifaJiaocheng/js/epub.min.js
WindowsAppYingyongKaifaJiaocheng/js/epub.min.map
WindowsAppYingyongKaifaJiaocheng/js/hooks.min.js
WindowsAppYingyongKaifaJiaocheng/js/hooks.min.map
WindowsAppYingyongKaifaJiaocheng/js/reader.js
WindowsAppYingyongKaifaJiaocheng/js/reader.js.map
WindowsAppYingyongKaifaJiaocheng/js/reader.min.js
WindowsAppYingyongKaifaJiaocheng/js/reader.min.map
WindowsAppYingyongKaifaJiaocheng/js/hooks/__init__.py
windows_app_yingyong_kaifa_jiaocheng-2024.3.3.0.dist-info/METADATA
windows_app_yingyong_kaifa_jiaocheng-2024.3.3.0.dist-info/WHEEL
windows_app_yingyong_kaifa_jiaocheng-2024.3.3.0.dist-info/entry_points.txt
windows_app_yingyong_kaifa_jiaocheng-2024.3.3.0.dist-info/top_level.txt
windows_app_yingyong_kaifa_jiaocheng-2024.3.3.0.dist-info/RECORD
